pypublibike/__init__.py
pypublibike/bike.py
pypublibike/constants.py
pypublibike/location.py
pypublibike/publibike.py
pypublibike/station.py
test/__init__.py
test/station_test.py
pypublibike-3.0.1.dist-info/LICENSE
pypublibike-3.0.1.dist-info/METADATA
pypublibike-3.0.1.dist-info/WHEEL
pypublibike-3.0.1.dist-info/top_level.txt
pypublibike-3.0.1.dist-info/RECORD
