Metadata-Version: 2.1
Name: pypublibike
Version: 3.0.1
Summary: A python wrapper around the PubliBike API
Home-page: https://github.com/eliabieri/pypublibike
Author: Elia Bieri
Author-email: bieri.elia@gmail.com
License: UNKNOWN
Platform: UNKNOWN
Classifier: Development Status :: 4 - Beta
Classifier: Intended Audience :: Developers
Classifier: Topic :: Internet
Classifier: License :: OSI Approved :: MIT License
Classifier: Programming Language :: Python :: 3.7
Classifier: Programming Language :: Python :: 3.8
Requires-Python: >=3.7
License-File: LICENSE
Requires-Dist: requests
Requires-Dist: haversine
